ytcl/__init__.py
ytcl/__main__.py
ytcl/ansi.py
ytcl/args.py
ytcl/base.py
ytcl/cancel.py
ytcl/cli.py
ytcl/config.py
ytcl/create.py
ytcl/error.py
ytcl/get.py
ytcl/http.py
ytcl/opts.py
ytcl/py.typed
ytcl/util.py
ytcl-1.1.0.dist-info/LICENSE
ytcl-1.1.0.dist-info/METADATA
ytcl-1.1.0.dist-info/WHEEL
ytcl-1.1.0.dist-info/entry_points.txt
ytcl-1.1.0.dist-info/top_level.txt
ytcl-1.1.0.dist-info/RECORD
