Metadata-Version: 2.1
Name: ytcl
Version: 1.1.0
Summary: CLI frontend for ytdl-server
Home-page: https://gitlab.com/adralioh/ytcl
Author: Adralioh
Keywords: ytdl-server,youtube-dl,yt-dlp,youtube,download,cli
Classifier: Development Status :: 5 - Production/Stable
Classifier: Environment :: Console
Classifier: Intended Audience :: End Users/Desktop
Classifier: License :: OSI Approved :: MIT License
Classifier: Operating System :: OS Independent
Classifier: Programming Language :: Python :: 3
Classifier: Topic :: Multimedia :: Video
Classifier: Topic :: System :: Archiving
Classifier: Typing :: Typed
Requires-Python: >=3.7
License-File: LICENSE
Provides-Extra: windows_color
Requires-Dist: colorama ; extra == 'windows_color'
